analysis/__init__.py
analysis/bmi_reconstruction.py
analysis/fa_decomp.py
analysis/performance_metrics.py
analysis/target_capture_task_analysis.py
built_in_tasks/__init__.py
built_in_tasks/bmimultitasks.py
built_in_tasks/manualcontrolmultitasks.py
built_in_tasks/othertasks.py
built_in_tasks/passivetasks.py
built_in_tasks/target_capture_task.py
built_in_tasks/target_graphics.py
built_in_tasks/target_tracking_task.py
config/__init__.py
config/bmiconfig.py
db/__init__.py
db/add_blackrock_datafiles_to_entry.py
db/boot_django.py
db/cleanup.py
db/compile_backup_list.py
db/db_settings.py
db/dbfunctions.py
db/maintenance.py
db/migrate_db.py
db/subclassdict.py
db/urls.py
db/tracker/__init__.py
db/tracker/admin.py
db/tracker/ajax.py
db/tracker/apps.py
db/tracker/celery.py
db/tracker/cloud.py
db/tracker/dbq.py
db/tracker/exp_tracker.py
db/tracker/jinja2.py
db/tracker/json_param.py
db/tracker/models.py
db/tracker/tasktrack.py
db/tracker/trainbmi.py
db/tracker/views.py
db/tracker/websocket.py
db/tracker/migrations/0001_initial.py
db/tracker/migrations/0002_auto_20191112_2306.py
db/tracker/migrations/0003_auto_20191113_2158.py
db/tracker/migrations/0004_keyvaluestore.py
db/tracker/migrations/0005_taskentry_sw_version.py
db/tracker/migrations/0006_datafile_backup_status.py
db/tracker/migrations/0007_taskentry_template.py
db/tracker/migrations/0008_taskentry_metadata.py
db/tracker/migrations/0009_auto_20210630_1019.py
db/tracker/migrations/0010_experimenter.py
db/tracker/migrations/0011_auto_20211017_1548.py
db/tracker/migrations/__init__.py
features/__init__.py
features/arduino_features.py
features/blackrock_features.py
features/bmi_task_features.py
features/debug_features.py
features/ecube_features.py
features/eyetracker_features.py
features/generator_features.py
features/hdf_features.py
features/kinarm_features.py
features/laser_features.py
features/neural_sys_features.py
features/optitrack_features.py
features/peripheral_device_features.py
features/phasespace_features.py
bmi3d-0.9.0.dist-info/LICENSE
bmi3d-0.9.0.dist-info/METADATA
bmi3d-0.9.0.dist-info/WHEEL
bmi3d-0.9.0.dist-info/top_level.txt
bmi3d-0.9.0.dist-info/RECORD
